LICENSE
MANIFEST.in
NOTES
README.md
setup.py
pyspark_db_utils/__init__.py
pyspark_db_utils/batch.py
pyspark_db_utils/get_jars.py
pyspark_db_utils/mogrify.py
pyspark_db_utils/read_from_db.py
pyspark_db_utils/write_to_db.py
pyspark_db_utils.egg-info/PKG-INFO
pyspark_db_utils.egg-info/SOURCES.txt
pyspark_db_utils.egg-info/dependency_links.txt
pyspark_db_utils.egg-info/not-zip-safe
pyspark_db_utils.egg-info/requires.txt
pyspark_db_utils.egg-info/top_level.txt
pyspark_db_utils/jars/clickhouse.jar
pyspark_db_utils/jars/postgresql.jar
pyspark_db_utils/utils/__init__.py
pyspark_db_utils/utils/db_connect.py
pyspark_db_utils/utils/ensure_columns_in_table.py
pyspark_db_utils/utils/ensure_from_expr.py
pyspark_db_utils/utils/execute_sql.py
pyspark_db_utils/utils/get_field_names.py
pyspark_db_utils/utils/table_exists.py
pyspark_db_utils/utils/spark/__init__.py
pyspark_db_utils/utils/spark/get_or_create_spark_session.py
pyspark_db_utils/utils/spark/get_spark_con_params.py
pyspark_db_utils/utils/spark/get_spark_conf.py