Metadata-Version: 1.1
Name: pyspark-db-utils
Version: 0.0.6
Summary: Usefull functions for working with Database in PySpark (PostgreSQL, ClickHouse)
Home-page: https://github.com/osahp/pyspark_db_utils
Author: Vladimir Smelov
Author-email: vsmelov@vsmelov.ru
License: MIT
Keywords: postgres postgresql clickhouse sql pyspark spark
Platform: UNKNOWN
Classifier: Development Status :: 3 - Alpha
Classifier: Programming Language :: Python :: 3
Classifier: Topic :: Database
Classifier: Topic :: Utilities
